Py4DMath/__init__.py
Py4DMath/matrix3d.py
Py4DMath/quaternion.py
Py4DMath/vector3d.py
Py4DMath/version.py
Py4DMath-1.0.0.dist-info/LICENSE.txt
Py4DMath-1.0.0.dist-info/METADATA
Py4DMath-1.0.0.dist-info/WHEEL
Py4DMath-1.0.0.dist-info/top_level.txt
Py4DMath-1.0.0.dist-info/RECORD
