Metadata-Version: 2.1
Name: Py4DMath
Version: 1.0.0
Summary: A math engine for controlling 3D objects
Author: Nicholas Chumney
License: MIT
License-File: LICENSE.txt
